{
  "$schema": "https://developer.microsoft.com/json-schemas/fabric/item/report/definition/visualContainer/2.7.0/schema.json",
  "name": "eb0695d39d5aedd68119",
  "position": {
    "x": 294.35322981285123,
    "y": 23.334803050609231,
    "z": 1500,
    "height": 69.878682842287688,
    "width": 77.642980935875215,
    "tabOrder": 36003
  },
  "visual": {
    "visualType": "clusteredColumnChart",
    "query": {
      "queryState": {
        "Category": {
          "projections": [
            {
              "field": {
                "Column": {
                  "Expression": {
                    "SourceRef": {
                      "Entity": "Fleet_Maintenance_Info(XL)"
                    }
                  },
                  "Property": "Technician"
                }
              },
              "queryRef": "Fleet_Maintenance_Info(XL).Technician",
              "nativeQueryRef": "Technician",
              "active": true
            }
          ]
        },
        "Y": {
          "projections": [
            {
              "field": {
                "Measure": {
                  "Expression": {
                    "SourceRef": {
                      "Entity": "Measures to calculate Techinician performance"
                    }
                  },
                  "Property": "Technician_Performance"
                }
              },
              "queryRef": "Measures to calculate Techinician performance.Technician_Performance",
              "nativeQueryRef": "Technician_Performance"
            }
          ]
        }
      },
      "sortDefinition": {
        "sort": [
          {
            "field": {
              "Measure": {
                "Expression": {
                  "SourceRef": {
                    "Entity": "Measures to calculate Techinician performance"
                  }
                },
                "Property": "Technician_Performance"
              }
            },
            "direction": "Ascending"
          }
        ]
      }
    },
    "objects": {
      "dataPoint": [
        {
          "properties": {
            "fill": {
              "solid": {
                "color": {
                  "expr": {
                    "Literal": {
                      "Value": "'#51AA5A'"
                    }
                  }
                }
              }
            }
          }
        }
      ]
    },
    "visualContainerObjects": {
      "title": [
        {
          "properties": {
            "text": {
              "expr": {
                "Literal": {
                  "Value": "'Top 10 Best Performing Vehicles'"
                }
              }
            },
            "show": {
              "expr": {
                "Literal": {
                  "Value": "false"
                }
              }
            },
            "titleWrap": {
              "expr": {
                "Literal": {
                  "Value": "true"
                }
              }
            },
            "alignment": {
              "expr": {
                "Literal": {
                  "Value": "'center'"
                }
              }
            },
            "fontSize": {
              "expr": {
                "Literal": {
                  "Value": "12D"
                }
              }
            }
          }
        }
      ],
      "background": [
        {
          "properties": {
            "show": {
              "expr": {
                "Literal": {
                  "Value": "false"
                }
              }
            },
            "transparency": {
              "expr": {
                "Literal": {
                  "Value": "0D"
                }
              }
            }
          }
        }
      ],
      "border": [
        {
          "properties": {
            "width": {
              "expr": {
                "Literal": {
                  "Value": "1D"
                }
              }
            }
          }
        }
      ],
      "dropShadow": [
        {
          "properties": {
            "show": {
              "expr": {
                "Literal": {
                  "Value": "false"
                }
              }
            }
          }
        }
      ],
      "padding": [
        {
          "properties": {
            "top": {
              "expr": {
                "Literal": {
                  "Value": "6D"
                }
              }
            },
            "left": {
              "expr": {
                "Literal": {
                  "Value": "8D"
                }
              }
            },
            "right": {
              "expr": {
                "Literal": {
                  "Value": "2D"
                }
              }
            }
          }
        }
      ]
    },
    "drillFilterOtherVisuals": true
  },
  "parentGroupName": "941ae13aa470af5f245b",
  "filterConfig": {
    "filters": [
      {
        "name": "2d587c04c34e370a202c",
        "ordinal": 0,
        "field": {
          "Column": {
            "Expression": {
              "SourceRef": {
                "Entity": "Fleet_Maintenance_Info(XL)"
              }
            },
            "Property": "Technician"
          }
        },
        "type": "TopN",
        "filter": {
          "Version": 2,
          "From": [
            {
              "Name": "subquery",
              "Expression": {
                "Subquery": {
                  "Query": {
                    "Version": 2,
                    "From": [
                      {
                        "Name": "f1",
                        "Entity": "Fleet_Maintenance_Info(XL)",
                        "Type": 0
                      },
                      {
                        "Name": "m",
                        "Entity": "Measures to calculate Techinician performance",
                        "Type": 0
                      }
                    ],
                    "Select": [
                      {
                        "Column": {
                          "Expression": {
                            "SourceRef": {
                              "Source": "f1"
                            }
                          },
                          "Property": "Technician"
                        },
                        "Name": "field"
                      }
                    ],
                    "OrderBy": [
                      {
                        "Direction": 2,
                        "Expression": {
                          "Measure": {
                            "Expression": {
                              "SourceRef": {
                                "Source": "m"
                              }
                            },
                            "Property": "Technician_Performance"
                          }
                        }
                      }
                    ],
                    "Top": 2
                  }
                }
              },
              "Type": 2
            },
            {
              "Name": "f1",
              "Entity": "Fleet_Maintenance_Info(XL)",
              "Type": 0
            }
          ],
          "Where": [
            {
              "Condition": {
                "In": {
                  "Expressions": [
                    {
                      "Column": {
                        "Expression": {
                          "SourceRef": {
                            "Source": "f1"
                          }
                        },
                        "Property": "Technician"
                      }
                    }
                  ],
                  "Table": {
                    "SourceRef": {
                      "Source": "subquery"
                    }
                  }
                }
              }
            }
          ]
        }
      },
      {
        "name": "5b10a03d57f4e62b19d9",
        "ordinal": 1,
        "field": {
          "Measure": {
            "Expression": {
              "SourceRef": {
                "Entity": "Measures to calculate Techinician performance"
              }
            },
            "Property": "Technician_Performance"
          }
        },
        "type": "Advanced"
      }
    ],
    "filterSortOrder": "Custom"
  }
}