{
  "$schema": "https://developer.microsoft.com/json-schemas/fabric/item/report/definition/visualContainer/2.7.0/schema.json",
  "name": "914e5e64888c867e9775",
  "position": {
    "x": 1028.8669201520913,
    "y": 220.95817490494298,
    "z": 2,
    "height": 125.56653992395437,
    "width": 203.43726235741445,
    "tabOrder": 2
  },
  "visual": {
    "visualType": "slicer",
    "query": {
      "queryState": {
        "Values": {
          "projections": [
            {
              "field": {
                "HierarchyLevel": {
                  "Expression": {
                    "Hierarchy": {
                      "Expression": {
                        "PropertyVariationSource": {
                          "Expression": {
                            "SourceRef": {
                              "Entity": "Date_Table"
                            }
                          },
                          "Name": "Variation",
                          "Property": "Date"
                        }
                      },
                      "Hierarchy": "Date Hierarchy"
                    }
                  },
                  "Level": "Year"
                }
              },
              "queryRef": "Date_Table.Date.Variation.Date Hierarchy.Year",
              "nativeQueryRef": "Date Year",
              "active": true
            },
            {
              "field": {
                "HierarchyLevel": {
                  "Expression": {
                    "Hierarchy": {
                      "Expression": {
                        "PropertyVariationSource": {
                          "Expression": {
                            "SourceRef": {
                              "Entity": "Date_Table"
                            }
                          },
                          "Name": "Variation",
                          "Property": "Date"
                        }
                      },
                      "Hierarchy": "Date Hierarchy"
                    }
                  },
                  "Level": "Quarter"
                }
              },
              "queryRef": "Date_Table.Date.Variation.Date Hierarchy.Quarter",
              "nativeQueryRef": "Date Quarter",
              "active": false
            },
            {
              "field": {
                "HierarchyLevel": {
                  "Expression": {
                    "Hierarchy": {
                      "Expression": {
                        "PropertyVariationSource": {
                          "Expression": {
                            "SourceRef": {
                              "Entity": "Date_Table"
                            }
                          },
                          "Name": "Variation",
                          "Property": "Date"
                        }
                      },
                      "Hierarchy": "Date Hierarchy"
                    }
                  },
                  "Level": "Month"
                }
              },
              "queryRef": "Date_Table.Date.Variation.Date Hierarchy.Month",
              "nativeQueryRef": "Date Month",
              "active": false
            },
            {
              "field": {
                "HierarchyLevel": {
                  "Expression": {
                    "Hierarchy": {
                      "Expression": {
                        "PropertyVariationSource": {
                          "Expression": {
                            "SourceRef": {
                              "Entity": "Date_Table"
                            }
                          },
                          "Name": "Variation",
                          "Property": "Date"
                        }
                      },
                      "Hierarchy": "Date Hierarchy"
                    }
                  },
                  "Level": "Day"
                }
              },
              "queryRef": "Date_Table.Date.Variation.Date Hierarchy.Day",
              "nativeQueryRef": "Date Day",
              "active": false
            }
          ]
        }
      }
    },
    "expansionStates": [
      {
        "roles": [
          "Values"
        ],
        "levels": [
          {
            "queryRefs": [
              "Date_Table.Date.Variation.Date Hierarchy.Year"
            ],
            "isCollapsed": true,
            "identityKeys": [
              {
                "Column": {
                  "Expression": {
                    "SourceRef": {
                      "Entity": "LocalDateTable_dae4be3b-bf5c-4b1c-915d-0ea18ead9e90"
                    }
                  },
                  "Property": "Year"
                }
              }
            ],
            "isPinned": true
          },
          {
            "queryRefs": [
              "Date_Table.Date.Variation.Date Hierarchy.Quarter"
            ],
            "isCollapsed": true,
            "isPinned": true
          },
          {
            "queryRefs": [
              "Date_Table.Date.Variation.Date Hierarchy.Month"
            ],
            "isCollapsed": true
          },
          {
            "queryRefs": [
              "Date_Table.Date.Variation.Date Hierarchy.Day"
            ],
            "isCollapsed": true
          }
        ],
        "root": {}
      }
    ],
    "objects": {
      "data": [
        {
          "properties": {
            "mode": {
              "expr": {
                "Literal": {
                  "Value": "'Basic'"
                }
              }
            }
          }
        }
      ],
      "general": [
        {
          "properties": {}
        }
      ]
    },
    "drillFilterOtherVisuals": true
  },
  "filterConfig": {
    "filters": [
      {
        "name": "4e2dfd819713e6cb733a",
        "field": {
          "HierarchyLevel": {
            "Expression": {
              "Hierarchy": {
                "Expression": {
                  "PropertyVariationSource": {
                    "Expression": {
                      "SourceRef": {
                        "Entity": "Date_Table"
                      }
                    },
                    "Name": "Variation",
                    "Property": "Date"
                  }
                },
                "Hierarchy": "Date Hierarchy"
              }
            },
            "Level": "Year"
          }
        },
        "type": "Advanced"
      },
      {
        "name": "29adb53e194965638220",
        "field": {
          "HierarchyLevel": {
            "Expression": {
              "Hierarchy": {
                "Expression": {
                  "PropertyVariationSource": {
                    "Expression": {
                      "SourceRef": {
                        "Entity": "Date_Table"
                      }
                    },
                    "Name": "Variation",
                    "Property": "Date"
                  }
                },
                "Hierarchy": "Date Hierarchy"
              }
            },
            "Level": "Quarter"
          }
        },
        "type": "Categorical"
      },
      {
        "name": "174bb2798439a4246b18",
        "field": {
          "HierarchyLevel": {
            "Expression": {
              "Hierarchy": {
                "Expression": {
                  "PropertyVariationSource": {
                    "Expression": {
                      "SourceRef": {
                        "Entity": "Date_Table"
                      }
                    },
                    "Name": "Variation",
                    "Property": "Date"
                  }
                },
                "Hierarchy": "Date Hierarchy"
              }
            },
            "Level": "Month"
          }
        },
        "type": "Categorical"
      },
      {
        "name": "222100d4633956d910c6",
        "field": {
          "HierarchyLevel": {
            "Expression": {
              "Hierarchy": {
                "Expression": {
                  "PropertyVariationSource": {
                    "Expression": {
                      "SourceRef": {
                        "Entity": "Date_Table"
                      }
                    },
                    "Name": "Variation",
                    "Property": "Date"
                  }
                },
                "Hierarchy": "Date Hierarchy"
              }
            },
            "Level": "Day"
          }
        },
        "type": "Categorical",
        "filter": {
          "Version": 2,
          "From": [
            {
              "Name": "l",
              "Entity": "LocalDateTable_dae4be3b-bf5c-4b1c-915d-0ea18ead9e90",
              "Type": 0
            }
          ],
          "Where": [
            {
              "Condition": {
                "Not": {
                  "Expression": {
                    "In": {
                      "Expressions": [
                        {
                          "Column": {
                            "Expression": {
                              "SourceRef": {
                                "Source": "l"
                              }
                            },
                            "Property": "Day"
                          }
                        }
                      ],
                      "Values": [
                        [
                          {
                            "Literal": {
                              "Value": "null"
                            }
                          }
                        ]
                      ]
                    }
                  }
                }
              },
              "Annotations": {
                "filterExpressionMetadata": {
                  "expressions": [
                    {
                      "HierarchyLevel": {
                        "Expression": {
                          "Hierarchy": {
                            "Expression": {
                              "PropertyVariationSource": {
                                "Expression": {
                                  "SourceRef": {
                                    "Entity": "Date_Table"
                                  }
                                },
                                "Name": "Variation",
                                "Property": "Date"
                              }
                            },
                            "Hierarchy": "Date Hierarchy"
                          }
                        },
                        "Level": "Day"
                      }
                    }
                  ],
                  "decomposedIdentities": {
                    "values": [
                      [
                        {
                          "0": [
                            {
                              "Literal": {
                                "Value": "null"
                              }
                            }
                          ]
                        }
                      ]
                    ],
                    "columns": [
                      {
                        "value": {
                          "Column": {
                            "Expression": {
                              "SourceRef": {
                                "Entity": "LocalDateTable_dae4be3b-bf5c-4b1c-915d-0ea18ead9e90"
                              }
                            },
                            "Property": "Day"
                          }
                        }
                      }
                    ]
                  },
                  "valueMap": [
                    {
                      "0": "(Blank)"
                    }
                  ]
                }
              }
            }
          ]
        },
        "objects": {
          "general": [
            {
              "properties": {
                "isInvertedSelectionMode": {
                  "expr": {
                    "Literal": {
                      "Value": "true"
                    }
                  }
                }
              }
            }
          ]
        }
      }
    ]
  }
}